LICENSE
MANIFEST.in
README.rst
setup.py
twixxy/__init__.py
twixxy/observer.py
twixxy.egg-info/PKG-INFO
twixxy.egg-info/SOURCES.txt
twixxy.egg-info/dependency_links.txt
twixxy.egg-info/requires.txt
twixxy.egg-info/top_level.txt
twixxy/features/__init__.py
twixxy/features/failure.py
twixxy/features/request.py