Metadata-Version: 1.0
Name: twixxy
Version: 0.1.1
Summary: Twisted integration with the twiggy logging library.
Home-page: https://github.com/dreid/twixxy
Author: David Reid
Author-email: dreid@dreid.org
License: MIT
Platform: UNKNOWN
